{
  "$schema": "https://developer.microsoft.com/json-schemas/fabric/item/report/definition/visualContainer/2.10.0/schema.json",
  "name": "8944b487a614f6074aae",
  "position": {
    "x": 1067,
    "y": 0,
    "z": 3000,
    "height": 172,
    "width": 213,
    "tabOrder": 5000
  },
  "visual": {
    "visualType": "cardVisual",
    "query": {
      "queryState": {
        "Data": {
          "projections": [
            {
              "field": {
                "Measure": {
                  "Expression": {
                    "SourceRef": {
                      "Entity": "Sales"
                    }
                  },
                  "Property": "Sales Per Sq Ft"
                }
              },
              "queryRef": "Sales.Sales Per Sq Ft",
              "nativeQueryRef": "Sales Per Sq Ft"
            }
          ]
        }
      },
      "sortDefinition": {
        "sort": [
          {
            "field": {
              "Measure": {
                "Expression": {
                  "SourceRef": {
                    "Entity": "Sales"
                  }
                },
                "Property": "Sales Per Sq Ft"
              }
            },
            "direction": "Descending"
          }
        ],
        "isDefaultSort": true
      }
    }
  }
}